cbr_fox/__init__.py
cbr_fox/adapters/__init__.py
cbr_fox/adapters/sktime_interface.py
cbr_fox/builder/__init__.py
cbr_fox/builder/cbr_fox_builder.py
cbr_fox/core/__init__.py
cbr_fox/core/cbr_fox.py
cbr_fox/custom_distance/__init__.py
cbr_fox/custom_distance/cci_distance.py
cbr_fox/utils/__init__.py
cbr_fox/utils/plot_utils.py
docs/source/conf.py
examples/Bitcoin_prediction/Bitcoin_Prediction.py
examples/Fraud_detection/Fraud_detection.py
examples/Power_consumption/Power_consumption.py
examples/Rainfall_prediction/Rainfall_prediction.py
examples/Romania_Power_Usage_Analysis_2016_2020_CBR-FoX/Romania_Power_Usage_Analysis_2016_2020_CBR-FoX.py
examples/Walmart_sales_prediction/Walmart_Sales_Prediction.py
examples/Weather_forecasting/Weather_Forecasting.py
examples/reproduce_all_figures/reproduce_all_figures.py
src/cbr_fox/__init__.py
src/cbr_fox/adapters/__init__.py
src/cbr_fox/adapters/sktime_interface.py
src/cbr_fox/builder/__init__.py
src/cbr_fox/builder/cbr_fox_builder.py
src/cbr_fox/core/__init__.py
src/cbr_fox/core/cbr_fox.py
src/cbr_fox/custom_distance/__init__.py
src/cbr_fox/custom_distance/cci_distance.py
src/cbr_fox/utils/__init__.py
src/cbr_fox/utils/plot_utils.py
tests/test_cbr_fox_basic.py
tests/test_cbr_fox_builder.py
cbr_fox-1.0.8.dist-info/METADATA
cbr_fox-1.0.8.dist-info/WHEEL
cbr_fox-1.0.8.dist-info/top_level.txt
cbr_fox-1.0.8.dist-info/RECORD
