Metadata-Version: 2.4
Name: CBR-FoX
Version: 1.0.8
Summary: A case-based reasoning python library that aims to help researchers find similar cases according to an input case with a wide range of methods that can detect similarity based on the features of each time series
Author-email: Gerardo Pérez <jerryperezperez@hotmail.com>, Moisés Valdez <moises.valdez.avila@gmail.com>
Maintainer-email: Gerardo Pérez <jerryperezperez@hotmail.com>, Moisés Valdez <moises.valdez.avila@gmail.com>
Project-URL: Documentation, https://CBRFoX.readthedocs.io
Project-URL: Repository, https://github.com/aaaimx/CBRFoX
Requires-Python: >=3.7
Requires-Dist: numpy>=2.0.0
Requires-Dist: pandas>=2.0.0
Requires-Dist: scikit-learn>=1.3
Requires-Dist: sktime>=0.38.5
Requires-Dist: scipy>=1.10
Requires-Dist: statsmodels>=0.14
Requires-Dist: matplotlib>=3.7
Requires-Dist: tqdm>=4.65
Requires-Dist: plotly>=6.0
Requires-Dist: joblib>=1.3
